omegalpes/__init__.py
omegalpes/actor/__init__.py
omegalpes/actor/actor.py
omegalpes/actor/operator_actors/__init__.py
omegalpes/actor/operator_actors/consumer_actors.py
omegalpes/actor/operator_actors/grid_operator_actors.py
omegalpes/actor/operator_actors/operator_actors.py
omegalpes/actor/operator_actors/producer_actors.py
omegalpes/actor/operator_actors/prosumer_actors.py
omegalpes/actor/operator_actors/supplier_actors.py
omegalpes/actor/project_developer_actors/__init__.py
omegalpes/actor/project_developer_actors/developper_actors.py
omegalpes/actor/regulator_actors/__init__.py
omegalpes/actor/regulator_actors/regulator_actors.py
omegalpes/energy/__init__.py
omegalpes/energy/energy_nodes.py
omegalpes/energy/energy_types.py
omegalpes/energy/exergy.py
omegalpes/energy/buildings/__init__.py
omegalpes/energy/buildings/thermal.py
omegalpes/energy/io/__init__.py
omegalpes/energy/io/poles.py
omegalpes/energy/units/__init__.py
omegalpes/energy/units/consumption_units.py
omegalpes/energy/units/conversion_units.py
omegalpes/energy/units/energy_units.py
omegalpes/energy/units/production_units.py
omegalpes/energy/units/reversible_units.py
omegalpes/energy/units/storage_units.py
omegalpes/general/__init__.py
omegalpes/general/time.py
omegalpes/general/optimisation/__init__.py
omegalpes/general/optimisation/core.py
omegalpes/general/optimisation/elements.py
omegalpes/general/optimisation/model.py
omegalpes/general/utils/__init__.py
omegalpes/general/utils/input_data.py
omegalpes/general/utils/maths.py
omegalpes/general/utils/output_data.py
omegalpes/general/utils/plots.py
omegalpes-0.5.0.dist-info/licenses/AUTHORS.rst
omegalpes-0.5.0.dist-info/licenses/LICENSE
omegalpes-0.5.0.dist-info/METADATA
omegalpes-0.5.0.dist-info/WHEEL
omegalpes-0.5.0.dist-info/top_level.txt
omegalpes-0.5.0.dist-info/RECORD
