Metadata-Version: 2.4
Name: omegalpes
Version: 0.5.0
Summary: OMEGAlpes is a linear energy systems modelling library
Author: B. DELINCHANT, S. HODENCQ, Y. MARECHAL, L. MORRIET, C. PAJOT, V. REINBOLD, F. WURTZ
Author-email: omegalpes-users@groupes.renater.fr
Classifier: Programming Language :: Python
Classifier: License :: OSI Approved :: Apache Software License
Classifier: Programming Language :: Python :: 3.12
Classifier: Topic :: Scientific/Engineering
License-File: LICENSE
License-File: AUTHORS.rst
Requires-Dist: PuLP>=3.1.1
Requires-Dist: Matplotlib>=3.10.3
Requires-Dist: Numpy>=2.2.6
Requires-Dist: Pandas>=2.2.3
Requires-Dist: lpfics>=0.0.1
Dynamic: author
Dynamic: author-email
Dynamic: classifier
Dynamic: description
Dynamic: description-content-type
Dynamic: license-file
Dynamic: requires-dist
Dynamic: summary
